lolpop/__init__.py
lolpop/base_integration.py
lolpop/cli/__init__.py
lolpop/cli/cli.py
lolpop/cli/create.py
lolpop/cli/datagen.py
lolpop/cli/deployment.py
lolpop/cli/extension.py
lolpop/cli/extensions/__init__.py
lolpop/cli/run.py
lolpop/cli/seed.py
lolpop/cli/test.py
lolpop/component/__init__.py
lolpop/component/base_component.py
lolpop/component/cache_manager/__init__.py
lolpop/component/cache_manager/base_cache_manager.py
lolpop/component/cache_manager/local_cache_manager.py
lolpop/component/data_checker/__init__.py
lolpop/component/data_checker/base_data_checker.py
lolpop/component/data_checker/deepchecks_data_checker.py
lolpop/component/data_checker/evidentlyai_data_checker.py
lolpop/component/data_checker/stumpy_matrix_profiler.py
lolpop/component/data_connector/__init__.py
lolpop/component/data_connector/base_data_connector.py
lolpop/component/data_connector/bigquery_data_connector.py
lolpop/component/data_connector/databricks_sql_data_connector.py
lolpop/component/data_connector/duckdb_data_connector.py
lolpop/component/data_connector/gcs_data_connector.py
lolpop/component/data_connector/local_data_connector.py
lolpop/component/data_connector/postgres_data_connector.py
lolpop/component/data_connector/redshift_data_connector.py
lolpop/component/data_connector/s3_data_connector.py
lolpop/component/data_connector/snowflake_data_connector.py
lolpop/component/data_profiler/__init__.py
lolpop/component/data_profiler/base_data_profiler.py
lolpop/component/data_profiler/evidentlyai_data_profiler.py
lolpop/component/data_profiler/sweetviz_data_profiler.py
lolpop/component/data_profiler/tslumen_data_profiler.py
lolpop/component/data_profiler/ydata_profiling_data_profiler.py
lolpop/component/data_splitter/__init__.py
lolpop/component/data_splitter/base_data_splitter.py
lolpop/component/data_splitter/local_data_splitter.py
lolpop/component/data_synthesizer/__init__.py
lolpop/component/data_synthesizer/base_data_synthesizer.py
lolpop-0.2.0.dist-info/LICENSE
lolpop-0.2.0.dist-info/METADATA
lolpop-0.2.0.dist-info/WHEEL
lolpop-0.2.0.dist-info/entry_points.txt
lolpop-0.2.0.dist-info/RECORD
